tsetmc_api/__init__.py
tsetmc_api/day_details/__init__.py
tsetmc_api/day_details/_core.py
tsetmc_api/day_details/day_details.py
tsetmc_api/day_details/orderbook.py
tsetmc_api/day_details/price.py
tsetmc_api/day_details/shareholder.py
tsetmc_api/day_details/threshold.py
tsetmc_api/day_details/trade.py
tsetmc_api/day_details/traders_type.py
tsetmc_api/group/__init__.py
tsetmc_api/group/_core.py
tsetmc_api/group/group.py
tsetmc_api/market_map/__init__.py
tsetmc_api/market_map/_core.py
tsetmc_api/market_map/map.py
tsetmc_api/market_watch/__init__.py
tsetmc_api/market_watch/_core.py
tsetmc_api/market_watch/daily_history.py
tsetmc_api/market_watch/orderbook.py
tsetmc_api/market_watch/price.py
tsetmc_api/market_watch/traders_type.py
tsetmc_api/market_watch/watch.py
tsetmc_api/symbol/__init__.py
tsetmc_api/symbol/_core.py
tsetmc_api/symbol/group.py
tsetmc_api/symbol/identification.py
tsetmc_api/symbol/notification.py
tsetmc_api/symbol/orderbook.py
tsetmc_api/symbol/price.py
tsetmc_api/symbol/shareholder.py
tsetmc_api/symbol/state_change.py
tsetmc_api/symbol/supervisor_message.py
tsetmc_api/symbol/symbol.py
tsetmc_api/symbol/traders_type.py
tsetmc_api/utils.py
tsetmc_api/version.py
tsetmc_api-5.3.0.dist-info/LICENSE.md
tsetmc_api-5.3.0.dist-info/METADATA
tsetmc_api-5.3.0.dist-info/WHEEL
tsetmc_api-5.3.0.dist-info/RECORD
