Metadata-Version: 2.1
Name: tsetmc-api
Version: 5.3.0
Summary: simple package to communicate and crawl data from tsetmc.com (Tehran Stock Exchange Website)
Home-page: https://github.com/mahs4d/tsetmc-api
License: MIT
Keywords: tsetmc,stocks,tehran stock exchange
Author: Mahdi Sadeghi
Author-email: mahdi74sadeghi@gmail.com
Requires-Python: >=3.10,<4.0
Classifier: License :: OSI Approved :: MIT License
Classifier: Programming Language :: Python :: 3
Classifier: Programming Language :: Python :: 3.10
Classifier: Programming Language :: Python :: 3.11
Requires-Dist: beautifulsoup4 (>=4.11.1,<5.0.0)
Requires-Dist: jdatetime (>=4.1.0,<5.0.0)
Requires-Dist: lxml (>=4.9.1,<5.0.0)
Requires-Dist: pydantic (>=1.10.2,<2.0.0)
Requires-Dist: python-dateutil (>=2.8.2,<3.0.0)
Requires-Dist: requests (>=2.28.1,<3.0.0)
Requires-Dist: schedule (>=1.1.0,<2.0.0)
Project-URL: Repository, https://github.com/mahs4d/tsetmc-api
